magic_proxy/__init__.py
magic_proxy/proxy.py
magic_proxy-0.2.0.dist-info/DESCRIPTION.rst
magic_proxy-0.2.0.dist-info/METADATA
magic_proxy-0.2.0.dist-info/RECORD
magic_proxy-0.2.0.dist-info/WHEEL
magic_proxy-0.2.0.dist-info/entry_points.txt
magic_proxy-0.2.0.dist-info/metadata.json
magic_proxy-0.2.0.dist-info/top_level.txt
magic_proxy-0.2.0.dist-info/zip-safe
