Metadata-Version: 2.0
Name: magic-proxy
Version: 0.2.0
Summary: A Simple HTTP proxy with extendability by middleware based plugins.
Home-page: https://github.com/restran/magic-proxy
Author: restran
Author-email: grestran@gmail.com
License: MIT
Keywords: python util
Platform: any
Classifier: Programming Language :: Python :: 2
Classifier: Programming Language :: Python :: 2.7
Classifier: Programming Language :: Python :: 3
Classifier: Programming Language :: Python :: 3.3
Classifier: Programming Language :: Python :: 3.4
Classifier: Programming Language :: Python :: 3.5
Classifier: Programming Language :: Python :: 3.6
Classifier: Programming Language :: Python :: Implementation :: CPython
Classifier: Programming Language :: Python :: Implementation :: PyPy
Requires-Dist: future
Requires-Dist: mountains
Requires-Dist: tornado
